pylin/__init__.py
pylin/driver.py
PyLin-0.2.7.dist-info/LICENSE.txt
PyLin-0.2.7.dist-info/METADATA
PyLin-0.2.7.dist-info/WHEEL
PyLin-0.2.7.dist-info/top_level.txt
PyLin-0.2.7.dist-info/RECORD
