Metadata-Version: 1.0
Name: PyLin
Version: 0.2.7
Summary: Lin Engineering step motor driver software.
Home-page: http://pypi.python.org/pypi/PyLin/
Author: Jan Offermann
Author-email: jano@uchicago.edu
License: LICENSE.txt
Platform: UNKNOWN
